MANIFEST.in
README.md
README.rst
deploy
setup.py
conf/conf.json.template
deployment/__init__.py
deployment/common.py
deployment/defaults.py
deployment/plugin.py
deployment/version.py
deployment/libs/__init__.py
deployment/libs/gitarchive.py
deployment/libs/mail.py
deployment/libs/prepender.py
deployment/plugins/__init__.py
deployment/plugins/info.py
deployment/plugins/mysql.py
deployment/plugins/src.py
deployment/plugins/supervisor.py
tnt_deployment.egg-info/PKG-INFO
tnt_deployment.egg-info/SOURCES.txt
tnt_deployment.egg-info/dependency_links.txt
tnt_deployment.egg-info/requires.txt
tnt_deployment.egg-info/top_level.txt