Metadata-Version: 1.1
Name: tnt-deployment
Version: 2.0.14
Summary: Deployment, provisioning and database migration tool.
Home-page: http://teonite.com/
Author: TEONITE
Author-email: kkrzysztofik@teonite.com
License: GPL 2.0
Platform: UNKNOWN
Classifier: Development Status :: 5 - Production/Stable
Classifier: License :: OSI Approved :: GNU General Public License v2 (GPLv2)
Classifier: Programming Language :: Python :: 2.7
Classifier: Topic :: Software Development :: Build Tools
